pinescript_syntax_checker/__init__.py
pinescript_syntax_checker/pinescript_checker.py
pinescript_syntax_checker/server.py
pinescript_syntax_checker-0.1.0.dist-info/METADATA
pinescript_syntax_checker-0.1.0.dist-info/WHEEL
pinescript_syntax_checker-0.1.0.dist-info/entry_points.txt
pinescript_syntax_checker-0.1.0.dist-info/licenses/LICENSE
pinescript_syntax_checker-0.1.0.dist-info/RECORD
