Metadata-Version: 2.4
Name: pinescript-syntax-checker
Version: 0.1.0
Summary: A Model Context Protocol (MCP) server for checking PineScript syntax using TradingView's API
Project-URL: Homepage, https://github.com/erevus-cn/pinescript-syntax-checker
Project-URL: Documentation, https://github.com/erevus-cn/pinescript-syntax-checker#readme
Project-URL: Repository, https://github.com/erevus-cn/pinescript-syntax-checker
Project-URL: Issues, https://github.com/erevus-cn/pinescript-syntax-checker/issues
Project-URL: Changelog, https://github.com/erevus-cn/pinescript-syntax-checker/blob/main/CHANGELOG.md
Author: erevus-cn
Maintainer: erevus-cn
License: MIT
License-File: LICENSE
Keywords: mcp,pinescript,syntax-checker,trading,tradingview
Classifier: Development Status :: 4 - Beta
Classifier: Intended Audience :: Developers
Classifier: License :: OSI Approved :: MIT License
Classifier: Operating System :: OS Independent
Classifier: Programming Language :: Python :: 3
Classifier: Programming Language :: Python :: 3.10
Classifier: Programming Language :: Python :: 3.11
Classifier: Programming Language :: Python :: 3.12
Classifier: Programming Language :: Python :: 3.13
Classifier: Topic :: Office/Business :: Financial :: Investment
Classifier: Topic :: Software Development :: Libraries :: Python Modules
Classifier: Topic :: Software Development :: Quality Assurance
Requires-Python: >=3.10
Requires-Dist: httpx>=0.28.1
Requires-Dist: mcp[cli]>=1.12.3
Requires-Dist: openai>=1.98.0
